mycalc/calculator.py
calc2243336-0.0.2.dist-info/METADATA
calc2243336-0.0.2.dist-info/WHEEL
calc2243336-0.0.2.dist-info/top_level.txt
calc2243336-0.0.2.dist-info/RECORD
